{
  "search_button": "Szukaj",
  "search_results": "Wyniki wyszukiwania",
  "no_results": "Nie znaleziono nieruchomości",
  "loading": "Ładowanie...",
  "view_details": "Zobacz szczegóły",
  "contact_agent": "Kontakt z agentem",
  "request_info": "Zapytaj o informacje",
  "share": "Udostępnij",
  "print": "Drukuj",
  "add_to_wishlist": "Dodaj do ulubionych",
  "remove_from_wishlist": "Usuń z ulubionych",
  "wishlist": "Ulubione",
  "my_wishlist": "Moje ulubione",
  "compare": "Porównaj",
  "back_to_results": "Powrót do wyników",
  "property_ref": "Numer ref.",
  "bedrooms": "Sypialnie",
  "bathrooms": "Łazienki",
  "bedroom": "Sypialnia",
  "bathroom": "Łazienka",
  "beds": "Syp.",
  "baths": "Łaz.",
  "price": "Cena",
  "list_price": "Cena",
  "price_on_request": "Cena na zapytanie",
  "price_from": "Cena od",
  "price_to": "Cena do",
  "min_price": "Cena min.",
  "max_price": "Cena maks.",
  "size": "Powierzchnia",
  "build_size": "Pow. użytkowa",
  "plot_size": "Pow. działki",
  "terrace_size": "Pow. tarasu",
  "interior_size": "Pow. wewnętrzna",
  "total_size": "Pow. całkowita",
  "sqm": "m²",
  "sqft": "stóp²",
  "location": "Lokalizacja",
  "area": "Obszar",
  "province": "Prowincja",
  "country": "Kraj",
  "all_locations": "Wszystkie lokalizacje",
  "select_location": "Wybierz lokalizację",
  "property_type": "Typ nieruchomości",
  "all_types": "Wszystkie typy",
  "select_type": "Wybierz typ",
  "listing_type": "Typ oferty",
  "for_sale": "Na sprzedaż",
  "for_rent": "Do wynajęcia",
  "resale": "Z rynku wtórnego",
  "resales": "Rynek wtórny",
  "new_development": "Nowe inwestycje",
  "new_developments": "Nowe inwestycje",
  "short_rental": "Wynajem krótkoterminowy",
  "short_rentals": "Wynajem krótkoterminowy",
  "long_rental": "Wynajem długoterminowy",
  "long_rentals": "Wynajem długoterminowy",
  "holiday_rental": "Wynajem wakacyjny",
  "features": "Cechy",
  "amenities": "Udogodnienia",
  "all_features": "Wszystkie cechy",
  "description": "Opis",
  "full_description": "Pełny opis",
  "property_details": "Szczegóły nieruchomości",
  "overview": "Przegląd",
  "specifications": "Specyfikacja",
  "energy_rating": "Klasa energetyczna",
  "year_built": "Rok budowy",
  "condition": "Stan",
  "orientation": "Orientacja",
  "views": "Widok",
  "parking": "Parking",
  "garage": "Garaż",
  "pool": "Basen",
  "private_pool": "Prywatny basen",
  "communal_pool": "Wspólny basen",
  "garden": "Ogród",
  "private_garden": "Prywatny ogród",
  "communal_garden": "Wspólny ogród",
  "terrace": "Taras",
  "sea_views": "Widok na morze",
  "mountain_views": "Widok na góry",
  "golf_views": "Widok na golf",
  "air_conditioning": "Klimatyzacja",
  "heating": "Ogrzewanie",
  "furnished": "Umeblowany",
  "unfurnished": "Nieumeblowany",
  "partly_furnished": "Częściowo umeblowany",
  "location_map": "Mapa",
  "street_view": "Widok ulicy",
  "virtual_tour": "Wirtualny spacer",
  "video": "Wideo",
  "photos": "Zdjęcia",
  "gallery": "Galeria",
  "floorplan": "Rzut",
  "detail_floor_plans": "Rzuty",
  "download_pdf": "Pobierz PDF",
  "per_month": "miesięcznie",
  "per_week": "tygodniowo",
  "per_night": "za noc",
  "from": "Od",
  "to": "Do",
  "min": "Min",
  "max": "Maks",
  "any": "Dowolny",
  "all": "Wszystkie",
  "reset": "Resetuj",
  "reset_filters": "Resetuj filtry",
  "apply_filters": "Zastosuj filtry",
  "advanced_search": "Wyszukiwanie zaawansowane",
  "more_filters": "Więcej filtrów",
  "less_filters": "Mniej filtrów",
  "show_more": "Pokaż więcej",
  "show_less": "Pokaż mniej",
  "sort_by": "Sortuj według",
  "sort_price_asc": "Cena: rosnąco",
  "sort_price_desc": "Cena: malejąco",
  "sort_date_asc": "Data: najstarsze",
  "sort_date_desc": "Data: najnowsze",
  "sort_size_asc": "Pow.: rosnąco",
  "sort_size_desc": "Pow.: malejąco",
  "sort_beds_asc": "Sypialnie: rosnąco",
  "sort_beds_desc": "Sypialnie: malejąco",
  "grid_view": "Widok siatki",
  "list_view": "Widok listy",
  "map_view": "Widok mapy",
  "results": "wyników",
  "properties": "nieruchomości",
  "property": "nieruchomość",
  "showing": "Pokazano",
  "of": "z",
  "page": "Strona",
  "previous": "Poprzednia",
  "next": "Następna",
  "first": "Pierwsza",
  "last": "Ostatnia",
  "status": "Status",
  "available": "Dostępny",
  "sold": "Sprzedany",
  "reserved": "Zarezerwowany",
  "under_offer": "W negocjacjach",
  "rented": "Wynajęty",
  "reduced": "Obniżona cena",
  "new_listing": "Nowy",
  "exclusive": "Ekskluzywny",
  "bank_repossession": "Nieruchomość bankowa",
  "fees": "Opłaty",
  "community_fees": "Opłaty wspólnoty",
  "ibi_tax": "Podatek IBI",
  "garbage_tax": "Opłata za śmieci",
  "notary_fees": "Opłaty notarialne",
  "registration_fees": "Opłaty rejestracyjne",
  "your_name": "Twoje imię",
  "your_email": "Twój e-mail",
  "your_phone": "Twój telefon",
  "your_message": "Twoja wiadomość",
  "send_message": "Wyślij wiadomość",
  "send_inquiry": "Wyślij zapytanie",
  "message_sent": "Wiadomość wysłana",
  "message_error": "Błąd wysyłania",
  "required_field": "Pole wymagane",
  "invalid_email": "Nieprawidłowy e-mail",
  "privacy_policy": "Polityka prywatności",
  "terms_conditions": "Regulamin",
  "accept_terms": "Akceptuję regulamin",
  "subscribe_newsletter": "Zapisz się do newslettera",
  "similar_properties": "Podobne nieruchomości",
  "nearby_properties": "Nieruchomości w pobliżu",
  "recently_viewed": "Ostatnio oglądane",
  "featured_properties": "Polecane",
  "latest_properties": "Najnowsze",
  "apartment": "Mieszkanie",
  "villa": "Willa",
  "townhouse": "Szeregowiec",
  "penthouse": "Penthouse",
  "house": "Dom",
  "bungalow": "Bungalow",
  "duplex": "Duplex",
  "studio": "Kawalerka",
  "land": "Grunt",
  "plot": "Działka",
  "commercial": "Lokal użytkowy",
  "office": "Biuro",
  "retail": "Sklep",
  "hotel": "Hotel",
  "restaurant": "Restauracja",
  "north": "Północ",
  "south": "Południe",
  "east": "Wschód",
  "west": "Zachód",
  "northeast": "Północny wschód",
  "northwest": "Północny zachód",
  "southeast": "Południowy wschód",
  "southwest": "Południowy zachód"
}
